package/__init__.py
exsadasdf-1.0.0.dist-info/METADATA
exsadasdf-1.0.0.dist-info/WHEEL
exsadasdf-1.0.0.dist-info/top_level.txt
exsadasdf-1.0.0.dist-info/RECORD
