Metadata-Version: 2.1
Name: exsadasdf
Version: 1.0.0
Summary: This is a new library
Author: New User
